CursorCreate/__init__.py
CursorCreate/cursorcreate.py
CursorCreate/gui/QtKit.py
CursorCreate/gui/__init__.py
CursorCreate/gui/cursorhotspotedit.py
CursorCreate/gui/cursorpreviewdialog.py
CursorCreate/gui/cursorselector.py
CursorCreate/gui/cursorthememaker.py
CursorCreate/gui/cursorviewedit.py
CursorCreate/gui/cursorviewer.py
CursorCreate/gui/layouts.py
CursorCreate/lib/__init__.py
CursorCreate/lib/ani_format.py
CursorCreate/lib/cur_format.py
CursorCreate/lib/cur_theme.py
CursorCreate/lib/cursor.py
CursorCreate/lib/cursor_util.py
CursorCreate/lib/format_core.py
CursorCreate/lib/theme_util.py
CursorCreate/lib/xcur_format.py
CursorCreate-1.4.0.dist-info/LICENSE
CursorCreate-1.4.0.dist-info/METADATA
CursorCreate-1.4.0.dist-info/WHEEL
CursorCreate-1.4.0.dist-info/entry_points.txt
CursorCreate-1.4.0.dist-info/top_level.txt
CursorCreate-1.4.0.dist-info/RECORD
