Metadata-Version: 2.1
Name: CursorCreate
Version: 1.4.0
Summary: A Multi-platform Cursor Theme Building Program
Home-page: https://github.com/isaacrobinson2000/CursorCreate
Download-URL: https://github.com/isaacrobinson2000/CursorCreate/archive/v1.3.1.tar.gz
Author: Isaac Robinson
Author-email: awesomeisaac2000@gmail.com
License: GPLv3
Platform: UNKNOWN
License-File: LICENSE
Requires-Dist: PySide6
Requires-Dist: Pillow
Requires-Dist: numpy
